wagtailfontawesomesvg/__init__.py
wagtail_font_awesome_svg-0.0.1.dist-info/LICENSE
wagtail_font_awesome_svg-0.0.1.dist-info/METADATA
wagtail_font_awesome_svg-0.0.1.dist-info/WHEEL
wagtail_font_awesome_svg-0.0.1.dist-info/top_level.txt
wagtail_font_awesome_svg-0.0.1.dist-info/RECORD
