Metadata-Version: 2.1
Name: wagtail-font-awesome-svg
Version: 0.0.1
Summary: Font Awesome icons as SVG for Wagtail
Home-page: https://github.com/allcaps/wagtail-font-awesome-svg
Author: Coen van der Kamp
Author-email: coen@fourdigits.nl
License: UNKNOWN
Platform: UNKNOWN
Classifier: Development Status :: 3 - Alpha
Classifier: Environment :: Web Environment
Classifier: Intended Audience :: Developers
Classifier: License :: OSI Approved :: SIL Open Font License 1.1 (OFL-1.1)
Classifier: License :: OSI Approved :: MIT License
Classifier: Operating System :: OS Independent
Classifier: Programming Language :: Python
Classifier: Framework :: Django
Classifier: Framework :: Django :: 2.2
Classifier: Framework :: Django :: 3.0
Classifier: Framework :: Django :: 3.1
Classifier: Framework :: Wagtail
Classifier: Framework :: Wagtail :: 2
Classifier: Topic :: Internet :: WWW/HTTP :: Site Management
Requires-Python: >=3.6
Requires-Dist: wagtail (>=2.10.1)
